cjm_nbdev_docments/__init__.py
cjm_nbdev_docments/_modidx.py
cjm_nbdev_docments/autofix.py
cjm_nbdev_docments/cli.py
cjm_nbdev_docments/core.py
cjm_nbdev_docments/report.py
cjm_nbdev_docments/scanner.py
cjm_nbdev_docments-0.0.11.dist-info/licenses/LICENSE
cjm_nbdev_docments-0.0.11.dist-info/METADATA
cjm_nbdev_docments-0.0.11.dist-info/WHEEL
cjm_nbdev_docments-0.0.11.dist-info/entry_points.txt
cjm_nbdev_docments-0.0.11.dist-info/top_level.txt
cjm_nbdev_docments-0.0.11.dist-info/RECORD
